ricxappframe/__init__.py
ricxappframe/constants.py
ricxappframe/xapp_frame.py
ricxappframe/xapp_rest.py
ricxappframe/xapp_rmr.py
ricxappframe/xapp_sdl.py
ricxappframe/xapp_subscribe.py
ricxappframe/xapp_symptomdata.py
ricxappframe/alarm/__init__.py
ricxappframe/alarm/alarm.py
ricxappframe/alarm/exceptions.py
ricxappframe/e2ap/__init__.py
ricxappframe/e2ap/asn1.py
ricxappframe/e2ap/asn1clib/__init__.py
ricxappframe/e2ap/asn1clib/asn1clib.py
ricxappframe/e2ap/asn1clib/types.py
ricxappframe/entities/__init__.py
ricxappframe/entities/rnib/__init__.py
ricxappframe/entities/rnib/additional_cell_information_pb2.py
ricxappframe/entities/rnib/cell_pb2.py
ricxappframe/entities/rnib/cells_pb2.py
ricxappframe/entities/rnib/e2node_component_config_pb2.py
ricxappframe/entities/rnib/enb_pb2.py
ricxappframe/entities/rnib/gnb_pb2.py
ricxappframe/entities/rnib/nb_identity_pb2.py
ricxappframe/entities/rnib/nb_types_pb2.py
ricxappframe/entities/rnib/nodeb_info_pb2.py
ricxappframe/entities/rnib/ran_function_pb2.py
ricxappframe/entities/rnib/ran_load_information_pb2.py
ricxappframe/entities/rnib/x2_setup_failure_response_pb2.py
ricxappframe/logger/__init__.py
ricxappframe/logger/mdclogger.py
ricxappframe/metric/__init__.py
ricxappframe/metric/exceptions.py
ricxappframe/metric/metric.py
ricxappframe/rmr/__init__.py
ricxappframe/rmr/exceptions.py
ricxappframe/rmr/helpers.py
ricxappframe/rmr/rmr.py
ricxappframe/rmr/rmr_mocks/__init__.py
ricxappframe/rmr/rmr_mocks/rmr_mocks.py
ricxappframe/rmr/rmrclib/__init__.py
ricxappframe/rmr/rmrclib/rmrclib.py
ricxappframe/subsclient/__init__.py
ricxappframe/subsclient/api_client.py
ricxappframe/subsclient/configuration.py
ricxappframe/subsclient/rest.py
ricxappframe/subsclient/api/__init__.py
ricxappframe/subsclient/api/common_api.py
ricxappframe/subsclient/api/xapp_api.py
ricxappframe/subsclient/models/__init__.py
ricxappframe/subsclient/models/action_definition.py
ricxappframe/subsclient/models/action_to_be_setup.py
ricxappframe-3.2.1.dist-info/LICENSE.txt
ricxappframe-3.2.1.dist-info/METADATA
ricxappframe-3.2.1.dist-info/WHEEL
ricxappframe-3.2.1.dist-info/top_level.txt
ricxappframe-3.2.1.dist-info/RECORD
