Metadata-Version: 2.1
Name: ricxappframe
Version: 3.2.1
Summary: Xapp and RMR framework for Python
Home-page: https://gerrit.o-ran-sc.org/r/admin/repos/ric-plt/xapp-frame-py
Author: O-RAN Software Community
License: Apache 2.0
Keywords: RIC xapp
Classifier: Development Status :: 4 - Beta
Classifier: Intended Audience :: Telecommunications Industry
Classifier: Programming Language :: Python :: 3
Classifier: License :: OSI Approved :: Apache Software License
Classifier: Operating System :: POSIX :: Linux
Classifier: Topic :: Communications
Requires-Python: >=3.7
License-File: LICENSE.txt
Requires-Dist: inotify-simple
Requires-Dist: msgpack
Requires-Dist: mdclogpy
Requires-Dist: ricsdl (<4.0.0,>=3.0.0)
Requires-Dist: requests
Requires-Dist: protobuf (<3.21.0)
Requires-Dist: inotify
